CHANGES.txt
buildout.cfg
setup.py
src/zc/__init__.py
src/zc.FileStorage.egg-info/PKG-INFO
src/zc.FileStorage.egg-info/SOURCES.txt
src/zc.FileStorage.egg-info/dependency_links.txt
src/zc.FileStorage.egg-info/namespace_packages.txt
src/zc.FileStorage.egg-info/not-zip-safe
src/zc.FileStorage.egg-info/requires.txt
src/zc.FileStorage.egg-info/top_level.txt
src/zc/FileStorage/__init__.py
src/zc/FileStorage/_zc_FileStorage_posix_fadvise.c
src/zc/FileStorage/blob_packing.txt
src/zc/FileStorage/tests.py