Metadata-Version: 1.0
Name: zc.FileStorage
Version: 1.2.0
Summary: New file-storage pack hack.
Home-page: UNKNOWN
Author: Jim Fulton
Author-email: jim@zope.com
License: ZPL 2.1
Platform: UNKNOWN
